neograd/__init__.py
neograd/autograd/__init__.py
neograd/autograd/graph.py
neograd/autograd/node.py
neograd/autograd/tensor.py
neograd/autograd/utils.py
neograd/autograd/ops/__init__.py
neograd/autograd/ops/basics.py
neograd/autograd/ops/conv.py
neograd/autograd/ops/operation.py
neograd/nn/__init__.py
neograd/nn/activations.py
neograd/nn/checkpoint.py
neograd/nn/loss.py
neograd/nn/model.py
neograd/nn/optim.py
neograd/nn/utils.py
neograd/nn/layers/__init__.py
neograd/nn/layers/conv.py
neograd/nn/layers/misc.py
neograd-0.0.4.dist-info/LICENSE.md
neograd-0.0.4.dist-info/METADATA
neograd-0.0.4.dist-info/WHEEL
neograd-0.0.4.dist-info/top_level.txt
neograd-0.0.4.dist-info/RECORD
