Metadata-Version: 2.1
Name: neograd
Version: 0.0.4
Summary: A deep learning framework created from scratch with Python and NumPy
Home-page: https://github.com/pranftw/neograd
Author: Pranav Sastry
Author-email: pranava.sri@gmail.com
Maintainer: Pranav Sastry
License: GPL-3.0
Keywords: python  ai  deep-learning  numpy automatic-differentiation  autograd neural-networks  pytorch-api
Requires-Python: >=3.7
License-File: LICENSE.md
Requires-Dist: numpy
Requires-Dist: dill
